[
  {
    "id": 401,
    "category": 1,
    "condition_type": 1,
    "condition_id": 0,
    "condition_num": 1,
    "name": "Visiting the hospital",
    "description": "Complete cumulative rewards for any of the items in Makai Hospital",
    "m_award_id": 401,
    "resource": "401"
  },
  {
    "id": 402,
    "category": 1,
    "condition_type": 1,
    "condition_id": 0,
    "condition_num": 3,
    "name": "Regular at Makai Hospital",
    "description": "Complete cumulative rewards for all items in Makai Hospital",
    "m_award_id": 402,
    "resource": "402"
  },
  {
    "id": 501,
    "category": 1,
    "condition_type": 2,
    "condition_id": 0,
    "condition_num": 50000,
    "name": "Prinny Dealer",
    "description": "50,000 Prinnies shipped from Prinny Prison",
    "m_award_id": 501,
    "resource": "501"
  },
  {
    "id": 502,
    "category": 1,
    "condition_type": 2,
    "condition_id": 0,
    "condition_num": 100000,
    "name": "Prinny Shipment King",
    "description": "100,000 Prinnies shipped from Prinny Prison",
    "m_award_id": 502,
    "resource": "502"
  },
  {
    "id": 601,
    "category": 1,
    "condition_type": 3,
    "condition_id": 0,
    "condition_num": 10,
    "name": "Mostly friends",
    "description": "Finish watching 10 character episodes",
    "m_award_id": 601,
    "resource": "601"
  },
  {
    "id": 602,
    "category": 1,
    "condition_type": 3,
    "condition_id": 0,
    "condition_num": 25,
    "name": "The evangelist of bonds",
    "description": "Finish watching 25 character episodes",
    "m_award_id": 602,
    "resource": "602"
  },
  {
    "id": 701,
    "category": 1,
    "condition_type": 4,
    "condition_id": 0,
    "condition_num": 200000,
    "name": "Workplaces for summer resorts",
    "description": "Increases labor force in in Etna's summer resort to over 200,000",
    "m_award_id": 701,
    "resource": "701"
  },
  {
    "id": 702,
    "category": 1,
    "condition_type": 4,
    "condition_id": 0,
    "condition_num": 400000,
    "name": "Those who control labor in summer resorts",
    "description": "Increases labor force in Etna's summer resort to over 400,000",
    "m_award_id": 702,
    "resource": "702"
  },
  {
    "id": 801,
    "category": 1,
    "condition_type": 5,
    "condition_id": 0,
    "condition_num": 250000,
    "name": "Those who develop summer resorts",
    "description": "Increases the amount of materials in Etna's summer resort to 250,000",
    "m_award_id": 801,
    "resource": "801"
  },
  {
    "id": 802,
    "category": 1,
    "condition_type": 5,
    "condition_id": 0,
    "condition_num": 500000,
    "name": "King of the Summer Resort",
    "description": "Increase the amount of materials in Etna's summer resort to 500,000",
    "m_award_id": 802,
    "resource": "802"
  },
  {
    "id": 901,
    "category": 1,
    "condition_type": 6,
    "condition_id": 0,
    "condition_num": 2500,
    "name": "Famous fishing fleets",
    "description": "Fishing fleet completed 2,500 expeditions",
    "m_award_id": 901,
    "resource": "901"
  },
  {
    "id": 902,
    "category": 1,
    "condition_type": 6,
    "condition_id": 0,
    "condition_num": 5000,
    "name": "The most dangerous fishing fleet in the universe",
    "description": "Fishing fleet completed 5,000 expeditions",
    "m_award_id": 902,
    "resource": "902"
  },
  {
    "id": 1001,
    "category": 1,
    "condition_type": 7,
    "condition_id": 0,
    "condition_num": 1500,
    "name": "A skilled bribe user",
    "description": "Use 1,500 bribes of any type",
    "m_award_id": 1001,
    "resource": "1001"
  },
  {
    "id": 1002,
    "category": 1,
    "condition_type": 7,
    "condition_id": 0,
    "condition_num": 3000,
    "name": "The manipulator of desires",
    "description": "Use 3,000 bribes of any type",
    "m_award_id": 1002,
    "resource": "1002"
  },
  {
    "id": 1101,
    "category": 1,
    "condition_type": 8,
    "condition_id": 0,
    "condition_num": 30,
    "name": "King lover",
    "description": "Own 30 King-type characters",
    "m_award_id": 1101,
    "resource": "1101"
  },
  {
    "id": 1102,
    "category": 1,
    "condition_type": 8,
    "condition_id": 0,
    "condition_num": 50,
    "name": "King Collector",
    "description": "Own 50 King-type characters",
    "m_award_id": 1102,
    "resource": "1102"
  },
  {
    "id": 1201,
    "category": 1,
    "condition_type": 9,
    "condition_id": 0,
    "condition_num": 30,
    "name": "Pawn lover",
    "description": "Own 30 Pawn-type characters",
    "m_award_id": 1201,
    "resource": "1201"
  },
  {
    "id": 1202,
    "category": 1,
    "condition_type": 9,
    "condition_id": 0,
    "condition_num": 50,
    "name": "Pawn Collector",
    "description": "Own 50 Pawn-type characters",
    "m_award_id": 1202,
    "resource": "1202"
  },
  {
    "id": 1301,
    "category": 1,
    "condition_type": 10,
    "condition_id": 0,
    "condition_num": 30,
    "name": "Rook lover",
    "description": "Own 30 Rook-type characters",
    "m_award_id": 1301,
    "resource": "1301"
  },
  {
    "id": 1302,
    "category": 1,
    "condition_type": 10,
    "condition_id": 0,
    "condition_num": 50,
    "name": "Rook Collector",
    "description": "Own 50 Rook-type characters",
    "m_award_id": 1302,
    "resource": "1302"
  },
  {
    "id": 1401,
    "category": 1,
    "condition_type": 11,
    "condition_id": 0,
    "condition_num": 30,
    "name": "Bishop lover",
    "description": "Own 30 Bishop-type characters",
    "m_award_id": 1401,
    "resource": "1401"
  },
  {
    "id": 1402,
    "category": 1,
    "condition_type": 11,
    "condition_id": 0,
    "condition_num": 50,
    "name": "Bishop Collector",
    "description": "Own 50 Bishop-type characters",
    "m_award_id": 1402,
    "resource": "1402"
  },
  {
    "id": 1501,
    "category": 1,
    "condition_type": 12,
    "condition_id": 0,
    "condition_num": 30,
    "name": "Knight lover",
    "description": "Own 30 Knight-type characters",
    "m_award_id": 1501,
    "resource": "1501"
  },
  {
    "id": 1502,
    "category": 1,
    "condition_type": 12,
    "condition_id": 0,
    "condition_num": 50,
    "name": "Knight Collector",
    "description": "Own 50 Kishop-type characters",
    "m_award_id": 1502,
    "resource": "1502"
  },
  {
    "id": 1601,
    "category": 1,
    "condition_type": 13,
    "condition_id": 0,
    "condition_num": 30,
    "name": "Queen lover",
    "description": "Own 30 Queen-type characters",
    "m_award_id": 1601,
    "resource": "1601"
  },
  {
    "id": 1602,
    "category": 1,
    "condition_type": 13,
    "condition_id": 0,
    "condition_num": 50,
    "name": "Queen Collector",
    "description": "Own 50 Queen-type characters",
    "m_award_id": 1602,
    "resource": "1602"
  },
  {
    "id": 1701,
    "category": 1,
    "condition_type": 14,
    "condition_id": 0,
    "condition_num": 10000,
    "name": "Regular members of the research team",
    "description": "Item World Research Team has reached MAX level equipment 10,000 times",
    "m_award_id": 1701,
    "resource": "1701"
  },
  {
    "id": 1702,
    "category": 1,
    "condition_type": 14,
    "condition_id": 0,
    "condition_num": 20000,
    "name": "Research Team VIP class specialists",
    "description": "Item World Research Team has reached MAX level equipment 20,000 times",
    "m_award_id": 1702,
    "resource": "1702"
  },
  {
    "id": 1801,
    "category": 1,
    "condition_type": 15,
    "condition_id": 0,
    "condition_num": 30,
    "name": "Super Reincarnation Repeater",
    "description": "Do super reincarnation 30 times",
    "m_award_id": 1801,
    "resource": "1801"
  },
  {
    "id": 1802,
    "category": 1,
    "condition_type": 15,
    "condition_id": 0,
    "condition_num": 150,
    "name": "The ultimate reincarnation",
    "description": "Do super reincarnation 150 times",
    "m_award_id": 1802,
    "resource": "1802"
  },
  {
    "id": 1901,
    "category": 1,
    "condition_type": 16,
    "condition_id": 0,
    "condition_num": 50,
    "name": "Blooming quality",
    "description": "Enhance Quality 50 times",
    "m_award_id": 1901,
    "resource": "1901"
  },
  {
    "id": 1902,
    "category": 1,
    "condition_type": 16,
    "condition_id": 0,
    "condition_num": 250,
    "name": "Overwhelming quality",
    "description": "Enhance Quality 250 times",
    "m_award_id": 1902,
    "resource": "1902"
  },
  {
    "id": 2001,
    "category": 1,
    "condition_type": 17,
    "condition_id": 0,
    "condition_num": 150,
    "name": "Weapon Collector",
    "description": "Gain 150 weapons",
    "m_award_id": 2001,
    "resource": "2001"
  },
  {
    "id": 2002,
    "category": 1,
    "condition_type": 17,
    "condition_id": 0,
    "condition_num": 300,
    "name": "A fanatic weapon collector",
    "description": "Gain 300 weapons",
    "m_award_id": 2002,
    "resource": "2002"
  },
  {
    "id": 2101,
    "category": 1,
    "condition_type": 18,
    "condition_id": 0,
    "condition_num": 75,
    "name": "Armor Collector",
    "description": "Get 75 different types of armor",
    "m_award_id": 2101,
    "resource": "2101"
  },
  {
    "id": 2102,
    "category": 1,
    "condition_type": 18,
    "condition_id": 0,
    "condition_num": 150,
    "name": "An fanatic armor collector",
    "description": "Gain 150 different types of armor",
    "m_award_id": 2102,
    "resource": "2102"
  },
  {
    "id": 2201,
    "category": 1,
    "condition_type": 19,
    "condition_id": 0,
    "condition_num": 50,
    "name": "Sword Master",
    "description": "Increase the proficiency level of the Sword weapon to level 50",
    "m_award_id": 2201,
    "resource": "2201"
  },
  {
    "id": 2301,
    "category": 1,
    "condition_type": 20,
    "condition_id": 0,
    "condition_num": 50,
    "name": "Fist Master",
    "description": "Increase the proficiency level of the Fist weapon to level 50",
    "m_award_id": 2301,
    "resource": "2301"
  },
  {
    "id": 2401,
    "category": 1,
    "condition_type": 21,
    "condition_id": 0,
    "condition_num": 50,
    "name": "Spear Master",
    "description": "Increase the proficiency level of the Spear weapon to level 50",
    "m_award_id": 2401,
    "resource": "2401"
  },
  {
    "id": 2501,
    "category": 1,
    "condition_type": 22,
    "condition_id": 0,
    "condition_num": 50,
    "name": "Bow Master",
    "description": "Increase the proficiency level of the Bow weapon to level 50",
    "m_award_id": 2501,
    "resource": "2501"
  },
  {
    "id": 2601,
    "category": 1,
    "condition_type": 23,
    "condition_id": 0,
    "condition_num": 50,
    "name": "Gun Master",
    "description": "Increase the proficiency level of the Gun weapon to level 50",
    "m_award_id": 2601,
    "resource": "2601"
  },
  {
    "id": 2701,
    "category": 1,
    "condition_type": 24,
    "condition_id": 0,
    "condition_num": 50,
    "name": "Axe Master",
    "description": "Increase the proficiency level of the Axe weapon to level 50",
    "m_award_id": 2701,
    "resource": "2701"
  },
  {
    "id": 2801,
    "category": 1,
    "condition_type": 25,
    "condition_id": 0,
    "condition_num": 50,
    "name": "Staff Master",
    "description": "Increase the proficiency level of the Staff weapon to level 50",
    "m_award_id": 2801,
    "resource": "2801"
  },
  {
    "id": 2901,
    "category": 1,
    "condition_type": 26,
    "condition_id": 0,
    "condition_num": 50,
    "name": "Monster Phys Master",
    "description": "Increase the proficiency level of the Monster Physical weapon to level 50",
    "m_award_id": 2901,
    "resource": "2901"
  },
  {
    "id": 3001,
    "category": 1,
    "condition_type": 27,
    "condition_id": 0,
    "condition_num": 50,
    "name": "Monster Magic Master",
    "description": "Increase the proficiency level of the Monster Magic weapon to level 50",
    "m_award_id": 3001,
    "resource": "3001"
  },
  {
    "id": 3101,
    "category": 1,
    "condition_type": 28,
    "condition_id": 0,
    "condition_num": 50,
    "name": "Super Magic Master Substitute Teacher",
    "description": "Unlock potential 50 times",
    "m_award_id": 3101,
    "resource": "3101"
  },
  {
    "id": 3102,
    "category": 1,
    "condition_type": 28,
    "condition_id": 0,
    "condition_num": 150,
    "name": "Super Magical License All Legend",
    "description": "Unlock potential 150 times",
    "m_award_id": 3102,
    "resource": "3102"
  },
  {
    "id": 3201,
    "category": 1,
    "condition_type": 29,
    "condition_id": 0,
    "condition_num": 1,
    "name": "Prinny friend",
    "description": "Level one prinny to level 9999",
    "m_award_id": 3201,
    "resource": "3201"
  },
  {
    "id": 3202,
    "category": 1,
    "condition_type": 29,
    "condition_id": 0,
    "condition_num": 4,
    "name": "Prinny lover",
    "description": "Level all four types of Prinny to level 9999",
    "m_award_id": 3202,
    "resource": "3202"
  },
  {
    "id": 3301,
    "category": 1,
    "condition_type": 30,
    "condition_id": 30137,
    "condition_num": 9999,
    "name": "Yellowtail fisherman",
    "description": "Make Space Yellowtail Level 9999",
    "m_award_id": 3301,
    "resource": "3301"
  },
  {
    "id": 3401,
    "category": 1,
    "condition_type": 31,
    "condition_id": 0,
    "condition_num": 1,
    "name": "Contest Fighting Spirit Award",
    "description": "Get one gold character badge at the Axel Contest",
    "m_award_id": 3401,
    "resource": "3401"
  },
  {
    "id": 3402,
    "category": 1,
    "condition_type": 31,
    "condition_id": 0,
    "condition_num": 3,
    "name": "Excellence of the contest",
    "description": "Get 3 gold character badges at the Axel Contest",
    "m_award_id": 3402,
    "resource": "3402"
  },
  {
    "id": 3501,
    "category": 2,
    "condition_type": 32,
    "condition_id": 0,
    "condition_num": 200000000,
    "name": "#NAME#I like it",
    "description": "#NAME#'s demon strength is over 200000000",
    "m_award_id": 3501,
    "resource": "3501"
  },
  {
    "id": 3701,
    "category": 1,
    "condition_type": 33,
    "condition_id": 0,
    "condition_num": 50000000,
    "name": "Final boss researcher",
    "description": "Your highest score over 50000000 at the Final Boss Lab",
    "m_award_id": 3701,
    "resource": "3701"
  },
  {
    "id": 3702,
    "category": 1,
    "condition_type": 33,
    "condition_id": 0,
    "condition_num": 200000000,
    "name": "The key to researching the final boss",
    "description": "Your highest score over 200000000 at the Final Boss Lab",
    "m_award_id": 3702,
    "resource": "3702"
  },
  {
    "id": 3703,
    "category": 1,
    "condition_type": 33,
    "condition_id": 0,
    "condition_num": 500000000,
    "name": "Ultimate final boss founder",
    "description": "Your highest score over 500000000 at the Final Boss Lab",
    "m_award_id": 3703,
    "resource": "3703"
  },
  {
    "id": 3801,
    "category": 1,
    "condition_type": 34,
    "condition_id": 5,
    "condition_num": 1,
    "name": "I love travel",
    "description": "Completely conquer the Demon World Exploration Tour",
    "m_award_id": 3801,
    "resource": "3801"
  },
  {
    "id": 3802,
    "category": 1,
    "condition_type": 34,
    "condition_id": 10,
    "condition_num": 1,
    "name": "Demon World Traveler",
    "description": "Completely conquer the Demon World Exploration Tour",
    "m_award_id": 3802,
    "resource": "3802"
  },
  {
    "id": 3803,
    "category": 1,
    "condition_type": 34,
    "condition_id": 21,
    "condition_num": 1,
    "name": "Travel Meister",
    "description": "Completely conquer the Shura Demon World Exploration Tour",
    "m_award_id": 3803,
    "resource": "3803"
  }
]